{
  "products": [
    {
      "id": 1,
      "title": "Alkalive Pure Drinking Water 200ml x 24",
      "titleAr": "مياه ألكالايف النقية للشرب 200 مل × 24",
      "handle": "alkalive-200ml-24",
      "vendor": "Alkalive",
      "productType": "water",
      "isNew": false,
      "isOffer": true,
      "variants": [
        {
          "id": 101,
          "title": "Default",
          "price": "4.0",
          "compareAtPrice": "8.0"
        }
      ],
      "image": "/alkalive-assets/200-2-e1744309014347.png",
      "images": [
        "/alkalive-assets/200-2-e1744309014347.png"
      ],
      "bodyHtml": "<p>This small and easy-to-use bottle is perfect for giving you the quick hydration you need during your daily activities.</p>",
      "descriptionAr": "تعتبر هذه الزجاجة الصغيرة وسهلة الاستخدام مثالية لمنحكم الترطيب السريع الذي تحتاجونه خلال أنشطتكم اليومية.",
      "tags": [
        "water",
        "200ml",
        "alkaline"
      ]
    },
    {
      "id": 2,
      "title": "Alkalive Pure Drinking Water 300ml x 12",
      "titleAr": "مياه ألكالايف النقية للشرب 300 مل × 12",
      "handle": "alkalive-300ml-12",
      "vendor": "Alkalive",
      "productType": "water",
      "isNew": false,
      "isOffer": true,
      "variants": [
        {
          "id": 102,
          "title": "Default",
          "price": "3.0",
          "compareAtPrice": "6.0"
        }
      ],
      "image": "/alkalive-assets/330-2-e1744299114337.png",
      "images": [
        "/alkalive-assets/330-2-e1744299114337.png"
      ],
      "bodyHtml": "<p>The ideal size for on-the-go hydration. Perfect for meetings, gym sessions, and outdoor activities.</p>",
      "descriptionAr": "الحجم المثالي للترطيب أثناء التنقل. مثالية للاجتماعات وجلسات الرياضة والأنشطة الخارجية.",
      "tags": [
        "water",
        "300ml",
        "alkaline"
      ]
    },
    {
      "id": 3,
      "title": "Alkalive Pure Drinking Water 500ml x 12",
      "titleAr": "مياه ألكالايف النقية للشرب 500 مل × 12",
      "handle": "alkalive-500ml-12",
      "vendor": "Alkalive",
      "productType": "water",
      "isNew": false,
      "isOffer": true,
      "variants": [
        {
          "id": 103,
          "title": "Default",
          "price": "3.5",
          "compareAtPrice": "7.0"
        }
      ],
      "image": "/alkalive-assets/500-2-e1744299282121.png",
      "images": [
        "/alkalive-assets/500-2-e1744299282121.png"
      ],
      "bodyHtml": "<p>Our most popular size. Perfect for daily hydration at work, home, or anywhere you go.</p>",
      "descriptionAr": "الحجم الأكثر شعبية لدينا. مثالي للترطيب اليومي في العمل أو المنزل أو أينما تذهب.",
      "tags": [
        "water",
        "500ml",
        "alkaline"
      ]
    },
    {
      "id": 4,
      "title": "Alkalive Pure Drinking Water 1500ml x 6",
      "titleAr": "مياه ألكالايف النقية للشرب 1500 مل × 6",
      "handle": "alkalive-1500ml-6",
      "vendor": "Alkalive",
      "productType": "water",
      "isNew": false,
      "isOffer": true,
      "variants": [
        {
          "id": 104,
          "title": "Default",
          "price": "3.25",
          "compareAtPrice": "6.5"
        }
      ],
      "image": "/alkalive-assets/1500-2-e1744299320277.png",
      "images": [
        "/alkalive-assets/1500-2-e1744299320277.png"
      ],
      "bodyHtml": "<p>The family size bottle. Ideal for home use and ensuring your family stays hydrated throughout the day.</p>",
      "descriptionAr": "زجاجة بحجم عائلي. مثالية للاستخدام المنزلي ولضمان بقاء عائلتك رطبة طوال اليوم.",
      "tags": [
        "water",
        "1500ml",
        "alkaline"
      ]
    },
    {
      "id": 5,
      "title": "Alkalive Baby Water 330ml x 12",
      "titleAr": "مياه ألكالايف للأطفال 330 مل × 12",
      "handle": "alkalive-baby-330ml-12",
      "vendor": "Alkalive",
      "productType": "water",
      "isNew": true,
      "isOffer": true,
      "variants": [
        {
          "id": 105,
          "title": "Default",
          "price": "3.75",
          "compareAtPrice": "7.5"
        }
      ],
      "image": "/alkalive-assets/prod-baby-330-individual.png",
      "images": [
        "/alkalive-assets/prod-baby-330-individual.png"
      ],
      "bodyHtml": "<p>Alkalive baby water is the perfect way to refresh your kids and add some hydration to their daily activities.</p>",
      "descriptionAr": "عبوة مياه ألكالايف للأطفال هي الطريقة المثلى لإنعاش أطفالك وإضافة بعض الترطيب إلى أنشطتهم اليومية.",
      "tags": [
        "water",
        "330ml",
        "baby",
        "alkaline"
      ]
    },
    {
      "id": 6,
      "title": "Alkalive Pure Drinking Water 200ml x 48",
      "titleAr": "مياه ألكالايف النقية للشرب 200 مل × 48",
      "handle": "alkalive-200ml-48",
      "vendor": "Alkalive",
      "productType": "water",
      "isNew": false,
      "isOffer": true,
      "variants": [
        {
          "id": 106,
          "title": "Default",
          "price": "5.25",
          "compareAtPrice": "10.5"
        }
      ],
      "image": "/alkalive-assets/200-2-e1744309014347.png",
      "images": [
        "/alkalive-assets/200-2-e1744309014347.png"
      ],
      "bodyHtml": "<p>Value pack of our 200ml bottles. Perfect for events, offices, and bulk purchases.</p>",
      "descriptionAr": "عبوة اقتصادية من زجاجات 200 مل. مثالية للفعاليات والمكاتب والشراء بالجملة.",
      "tags": [
        "water",
        "200ml",
        "alkaline",
        "bulk"
      ]
    },
    {
      "id": 7,
      "title": "Alkalive Pure Drinking Water 500ml x 24",
      "titleAr": "مياه ألكالايف النقية للشرب 500 مل × 24",
      "handle": "alkalive-500ml-24",
      "vendor": "Alkalive",
      "productType": "water",
      "isNew": false,
      "isOffer": true,
      "variants": [
        {
          "id": 107,
          "title": "Default",
          "price": "4.5",
          "compareAtPrice": "9.0"
        }
      ],
      "image": "/alkalive-assets/500-2-e1744299282121.png",
      "images": [
        "/alkalive-assets/500-2-e1744299282121.png"
      ],
      "bodyHtml": "<p>Value pack of our 500ml bottles. The best choice for offices and families.</p>",
      "descriptionAr": "عبوة اقتصادية من زجاجات 500 مل. الخيار الأفضل للمكاتب والعائلات.",
      "tags": [
        "water",
        "500ml",
        "alkaline",
        "bulk"
      ]
    },
    {
      "id": 8,
      "title": "Alkalive Pure Drinking Water 1500ml x 12",
      "titleAr": "مياه ألكالايف النقية للشرب 1500 مل × 12",
      "handle": "alkalive-1500ml-12",
      "vendor": "Alkalive",
      "productType": "water",
      "isNew": false,
      "isOffer": true,
      "variants": [
        {
          "id": 108,
          "title": "Default",
          "price": "6.0",
          "compareAtPrice": "12.0"
        }
      ],
      "image": "/alkalive-assets/1500-2-e1744299320277.png",
      "images": [
        "/alkalive-assets/1500-2-e1744299320277.png"
      ],
      "bodyHtml": "<p>Bulk pack of our family-size 1500ml bottles. Stock up and save.</p>",
      "descriptionAr": "عبوة كبيرة من زجاجات 1500 مل العائلية. اشترِ بالجملة ووفّر.",
      "tags": [
        "water",
        "1500ml",
        "alkaline",
        "bulk"
      ]
    },
    {
      "id": 9,
      "title": "Alkalive Alkaline Drinking Water 330ml x 24",
      "titleAr": "مياه الشرب القلوية 330 مل × 24",
      "handle": "alkalive-all-sizes",
      "vendor": "Alkalive",
      "productType": "water",
      "isNew": false,
      "isOffer": true,
      "variants": [
        {
          "id": 109,
          "title": "Default",
          "price": "5.38",
          "compareAtPrice": "10.75"
        }
      ],
      "image": "/alkalive-assets/prod-all-sizes.png",
      "images": [
        "/alkalive-assets/prod-all-sizes.png"
      ],
      "bodyHtml": "<p>We offer you mineral-rich water in a unique design. Available in various sizes.</p>",
      "descriptionAr": "نقدم لكم المياه الغنية بالمعادن في تصميم فريد من نوعه. متوفرة في مختلف الأحجام لمرافقتك في أي مناسبة ولتلبية جميع احتياجاتك.",
      "tags": [
        "water",
        "alkaline",
        "all-sizes"
      ]
    },
    {
      "id": 10,
      "title": "Alkalive Water 250ml x 24",
      "titleAr": "مياه ألكالايف 250 مل × 24",
      "handle": "alkalive-250ml",
      "vendor": "Alkalive",
      "productType": "water",
      "isNew": true,
      "isOffer": true,
      "variants": [
        {
          "id": 110,
          "title": "Default",
          "price": "5.25",
          "compareAtPrice": "10.5"
        }
      ],
      "image": "/alkalive-assets/prod-250ml-individual.png",
      "images": [
        "/alkalive-assets/prod-250ml-individual.png"
      ],
      "bodyHtml": "<p>Stay refreshed with the Alkalive 250ml bottle.</p>",
      "descriptionAr": "ابقَ منتعشًا مع زجاجة ألكالايف بسعة 250 مل، المصممة خصيصًا لأسلوب حياتك النشط.",
      "tags": [
        "water",
        "250ml",
        "alkaline"
      ]
    },
    {
      "id": 11,
      "title": "Alkalive Play & Go - Pink 250ml x 24",
      "titleAr": "ألكالايف بلاي آند جو – وردي 250 مل × 24",
      "handle": "alkalive-play-go-pink",
      "vendor": "Alkalive",
      "productType": "water",
      "isNew": true,
      "isOffer": true,
      "variants": [
        {
          "id": 111,
          "title": "Default",
          "price": "7.5",
          "compareAtPrice": "15.0"
        }
      ],
      "image": "/alkalive-assets/prod-play-go-pink-individual.png",
      "images": [
        "/alkalive-assets/prod-play-go-pink-individual.png"
      ],
      "bodyHtml": "<p>A fun little bottle designed for daily hydration.</p>",
      "descriptionAr": "زجاجة صغيرة ممتعة مصممة للترطيب اليومي. بفضل ملصقها الوردي المرح وغطائها السهل الفتح والإغلاق.",
      "tags": [
        "water",
        "250ml",
        "baby",
        "kids"
      ]
    },
    {
      "id": 12,
      "title": "Alkalive Play & Go - Blue 250ml x 24",
      "titleAr": "ألكالاييف بلاي آند جو – أزرق 250 مل × 24",
      "handle": "alkalive-play-go-blue",
      "vendor": "Alkalive",
      "productType": "water",
      "isNew": true,
      "isOffer": true,
      "variants": [
        {
          "id": 112,
          "title": "Default",
          "price": "7.5",
          "compareAtPrice": "15.0"
        }
      ],
      "image": "/alkalive-assets/prod-play-go-blue-individual.png",
      "images": [
        "/alkalive-assets/prod-play-go-blue-individual.png"
      ],
      "bodyHtml": "<p>Pure refreshment in a small, on-the-go size.</p>",
      "descriptionAr": "انتعاش نقي في حجم صغير مثالي للتنقل. يأتي بملصق أزرق أنيق وغطاء لولبي ذكي.",
      "tags": [
        "water",
        "250ml",
        "baby",
        "kids"
      ]
    },
    {
      "id": 13,
      "title": "Alkalive Baby Water 330ml x 24",
      "titleAr": "مياه ألكالايف للأطفال 330 مل × 24",
      "handle": "alkalive-baby-330ml",
      "vendor": "Alkalive",
      "productType": "water",
      "isNew": true,
      "isOffer": true,
      "variants": [
        {
          "id": 113,
          "title": "Default",
          "price": "10.0",
          "compareAtPrice": "20.0"
        }
      ],
      "image": "/alkalive-assets/prod-baby-330-individual.png",
      "images": [
        "/alkalive-assets/prod-baby-330-individual.png"
      ],
      "bodyHtml": "<p>Alkalive baby water is the perfect way to refresh your kids.</p>",
      "descriptionAr": "عبوة مياه ألكالايف للأطفال هي الطريقة المثلى لإنعاش أطفالك وإضافة بعض الترطيب إلى أنشطتهم اليومية.",
      "tags": [
        "water",
        "330ml",
        "baby",
        "alkaline"
      ]
    },
    {
      "id": 14,
      "title": "Alkalive Sport Bottle 750ml x 6",
      "titleAr": "زجاجة رياضية 750 مل × 6",
      "handle": "alkalive-sport-750ml-6",
      "vendor": "Alkalive",
      "productType": "water",
      "isNew": false,
      "isOffer": true,
      "variants": [
        {
          "id": 114,
          "title": "Default",
          "price": "4.38",
          "compareAtPrice": "8.75"
        }
      ],
      "image": "/alkalive-assets/prod-1500ml-individual.png",
      "images": [
        "/alkalive-assets/prod-1500ml-individual.png"
      ],
      "bodyHtml": "<p>The family size bottle. Ideal for home use.</p>",
      "descriptionAr": "ابق منتعشًا ونشطًا مع الزجاجة الرياضية سعة 750 مل. مصممة لأسلوب حياة نشيط، فهي توفر ترطيبًا و انتعاشًا أثناء التنقل.",
      "tags": [
        "water",
        "1500ml",
        "alkaline"
      ]
    },
    {
      "id": 16,
      "title": "Alkalive Glass Bottle 250ml x 6",
      "titleAr": "الكالايف في زجاج 250 مل × 6",
      "handle": "alkalive-glass-250ml",
      "vendor": "Alkalive",
      "productType": "glass",
      "isNew": false,
      "isOffer": true,
      "variants": [
        {
          "id": 116,
          "title": "Default",
          "price": "6.75",
          "compareAtPrice": "13.5"
        }
      ],
      "image": "/alkalive-assets/prod-sport-individual.png",
      "images": [
        "/alkalive-assets/prod-sport-individual.png"
      ],
      "bodyHtml": "<p>The premium hydration experience in elegant glass.</p>",
      "descriptionAr": "تجربة الترطيب المتميزة في زجاجة زجاجية أنيقة سعة 250 مل.",
      "tags": [
        "water",
        "glass",
        "premium",
        "250ml"
      ]
    },
    {
      "id": 32,
      "title": "Alkalive 5 Gallon Non-Returnable",
      "titleAr": "ألكالايف 5 جالون غير قابلة للإرجاع",
      "handle": "alkalive-5gallon-non-returnable",
      "vendor": "Alkalive",
      "productType": "Water",
      "descriptionAr": "عبوة مياه ألكالايف القلوية النقية سعة 5 جالون (19 لتر) غير قابلة للإرجاع. مثالية للاستخدام المنزلي والمكتبي مع أجهزة تبريد المياه.",
      "bodyHtml": "عبوة مياه ألكالايف القلوية النقية سعة 5 جالون غير قابلة للإرجاع.",
      "image": "/alkalive-assets/prod-5gallon-nonreturnable.png",
      "images": [
        "/alkalive-assets/prod-5gallon-nonreturnable.png"
      ],
      "variants": [
        {
          "id": 131,
          "price": "4.0",
          "compareAtPrice": "8.0",
          "title": "Default"
        }
      ],
      "collections": [
        "5-gallon",
        "alkalive-water"
      ],
      "tags": [
        "5-gallon",
        "non-returnable",
        "alkalive"
      ],
      "isOffer": true
    },
    {
      "id": 33,
      "title": "Alkalive 5 Gallon Returnable",
      "titleAr": "ألكالايف 5 جالون قابلة للإرجاع",
      "handle": "alkalive-5gallon-returnable",
      "vendor": "Alkalive",
      "productType": "Water",
      "descriptionAr": "عبوة مياه ألكالايف القلوية النقية سعة 5 جالون (19 لتر) قابلة للإرجاع. مصنوعة من البولي كربونات المتين، مثالية للاستخدام المتكرر مع أجهزة تبريد المياه.",
      "bodyHtml": "عبوة مياه ألكالايف القلوية النقية سعة 5 جالون قابلة للإرجاع.",
      "image": "/alkalive-assets/prod-5gallon-returnable.png",
      "images": [
        "/alkalive-assets/prod-5gallon-returnable.png"
      ],
      "variants": [
        {
          "id": 132,
          "price": "2.5",
          "compareAtPrice": "5.0",
          "title": "Default"
        }
      ],
      "collections": [
        "5-gallon",
        "alkalive-water"
      ],
      "tags": [
        "5-gallon",
        "returnable",
        "alkalive"
      ],
      "isOffer": true
    },
    {
      "id": 17,
      "title": "Alkalive Glass Bottle 330ml x 6",
      "titleAr": "الكالايف في زجاج 330 مل × 6",
      "handle": "alkalive-glass-330ml",
      "vendor": "Alkalive",
      "productType": "glass",
      "isNew": false,
      "isOffer": true,
      "variants": [
        {
          "id": 117,
          "title": "Default",
          "price": "9.0",
          "compareAtPrice": "18.0"
        }
      ],
      "image": "/alkalive-assets/prod-sport-individual.png",
      "images": [
        "/alkalive-assets/prod-sport-individual.png"
      ],
      "bodyHtml": "<p>The premium hydration experience in elegant glass.</p>",
      "descriptionAr": "تجربة الترطيب المتميزة في زجاجة زجاجية أنيقة سعة 330 مل.",
      "tags": [
        "water",
        "glass",
        "premium",
        "330ml"
      ]
    },
    {
      "id": 18,
      "title": "Alkalive Glass Bottle 750ml x 6",
      "titleAr": "الكالايف في زجاج 750 مل × 6",
      "handle": "alkalive-glass-750ml",
      "vendor": "Alkalive",
      "productType": "glass",
      "isNew": false,
      "isOffer": true,
      "variants": [
        {
          "id": 118,
          "title": "Default",
          "price": "18.0",
          "compareAtPrice": "36.0"
        }
      ],
      "image": "/alkalive-assets/prod-sport-individual.png",
      "images": [
        "/alkalive-assets/prod-sport-individual.png"
      ],
      "bodyHtml": "<p>The premium hydration experience in elegant glass.</p>",
      "descriptionAr": "تجربة الترطيب المتميزة في زجاجة زجاجية أنيقة سعة 750 مل.",
      "tags": [
        "water",
        "glass",
        "premium",
        "750ml"
      ]
    },
    {
      "id": 19,
      "title": "Sparkalive 250ml x 6",
      "titleAr": "سباركالايف 250 مل × 6",
      "handle": "sparkalive-250ml",
      "vendor": "Alkalive",
      "productType": "sparkling",
      "isNew": false,
      "isOffer": true,
      "variants": [
        {
          "id": 119,
          "title": "Default",
          "price": "8.25",
          "compareAtPrice": "16.5"
        }
      ],
      "image": "/alkalive-assets/prod-glass-individual.png",
      "images": [
        "/alkalive-assets/prod-glass-individual.png"
      ],
      "bodyHtml": "<p>Discover Sparkalive, the first Qatari sparkling water.</p>",
      "descriptionAr": "اكتشف سباركلايف، أول مياه فوارة قطرية سعة 250 مل.",
      "tags": [
        "sparkling",
        "water",
        "250ml"
      ]
    },
    {
      "id": 20,
      "title": "Sparkalive 330ml x 6",
      "titleAr": "سباركالايف 330 مل × 6",
      "handle": "sparkalive-330ml",
      "vendor": "Alkalive",
      "productType": "sparkling",
      "isNew": false,
      "isOffer": true,
      "variants": [
        {
          "id": 120,
          "title": "Default",
          "price": "10.5",
          "compareAtPrice": "21.0"
        }
      ],
      "image": "/alkalive-assets/prod-glass-individual.png",
      "images": [
        "/alkalive-assets/prod-glass-individual.png"
      ],
      "bodyHtml": "<p>Discover Sparkalive, the first Qatari sparkling water.</p>",
      "descriptionAr": "اكتشف سباركلايف، أول مياه فوارة قطرية سعة 330 مل.",
      "tags": [
        "sparkling",
        "water",
        "330ml"
      ]
    },
    {
      "id": 21,
      "title": "Sparkalive 750ml x 6",
      "titleAr": "سباركالايف 750 مل × 6",
      "handle": "sparkalive-750ml",
      "vendor": "Alkalive",
      "productType": "sparkling",
      "isNew": false,
      "isOffer": true,
      "variants": [
        {
          "id": 121,
          "title": "Default",
          "price": "19.5",
          "compareAtPrice": "39.0"
        }
      ],
      "image": "/alkalive-assets/prod-glass-individual.png",
      "images": [
        "/alkalive-assets/prod-glass-individual.png"
      ],
      "bodyHtml": "<p>Discover Sparkalive, the first Qatari sparkling water.</p>",
      "descriptionAr": "اكتشف سباركلايف، أول مياه فوارة قطرية سعة 750 مل.",
      "tags": [
        "sparkling",
        "water",
        "750ml"
      ]
    },
    {
      "id": 22,
      "title": "Sparkalive Lemon & Mint 250ml x 6",
      "titleAr": "سباركالايف بنكهة الليمون و النعناع 250 مل × 6",
      "handle": "sparkalive-lemon-mint-250ml",
      "vendor": "Alkalive",
      "productType": "sparkling",
      "isNew": false,
      "isOffer": true,
      "variants": [
        {
          "id": 122,
          "title": "Default",
          "price": "9.0",
          "compareAtPrice": "18.0"
        }
      ],
      "image": "/alkalive-assets/prod-sparkalive-lemon-individual.png",
      "images": [
        "/alkalive-assets/prod-sparkalive-lemon-individual.png"
      ],
      "bodyHtml": "<p>Experience sparkling water with Sparkalive lemon and mint.</p>",
      "descriptionAr": "استمتع بتجربة المياه الفوارة مع سباركلايف بنكهة الليمون والنعناع سعة 250 مل.",
      "tags": [
        "sparkling",
        "flavored",
        "lemon",
        "mint",
        "250ml"
      ]
    },
    {
      "id": 23,
      "title": "Sparkalive Mango Peach 250ml x 6",
      "titleAr": "سباركالايف بنكهة المانجو خوخ 250 مل × 6",
      "handle": "sparkalive-mango-peach-250ml",
      "vendor": "Alkalive",
      "productType": "sparkling",
      "isNew": false,
      "isOffer": true,
      "variants": [
        {
          "id": 123,
          "title": "Default",
          "price": "9.0",
          "compareAtPrice": "18.0"
        }
      ],
      "image": "/alkalive-assets/prod-sparkalive-mango-individual.png",
      "images": [
        "/alkalive-assets/prod-sparkalive-mango-individual.png"
      ],
      "bodyHtml": "<p>Unleash the fruit delight with Sparkalive Mango Peach.</p>",
      "descriptionAr": "أطلق العنان لبهجة الفواكه مع سباركلايف بنكهة المانجو والخوخ سعة 250 مل.",
      "tags": [
        "sparkling",
        "flavored",
        "mango",
        "peach",
        "250ml"
      ]
    },
    {
      "id": 24,
      "title": "Alkablack 330ml x 6",
      "titleAr": "الكابلاك 330 مل × 6",
      "handle": "alkablack-330ml",
      "vendor": "Alkalive",
      "productType": "premium",
      "isNew": false,
      "isOffer": true,
      "variants": [
        {
          "id": 124,
          "title": "Default",
          "price": "24.0",
          "compareAtPrice": "48.0"
        }
      ],
      "image": "/alkalive-assets/prod-alkablack-individual.png",
      "images": [
        "/alkalive-assets/prod-alkablack-individual.png"
      ],
      "bodyHtml": "<p>Discover the power of Alkablack, a premium black water.</p>",
      "descriptionAr": "اكتشف قوة الكابلاك، ماء أسود فاخر مصمم لتحسين صحتك سعة 330 مل.",
      "tags": [
        "premium",
        "black-water",
        "fulvic",
        "330ml"
      ]
    },
    {
      "id": 25,
      "title": "Sparkablack 330ml x 6",
      "titleAr": "سباركابلاك 330 مل × 6",
      "handle": "sparkablack-330ml",
      "vendor": "Alkalive",
      "productType": "premium",
      "isNew": false,
      "isOffer": true,
      "variants": [
        {
          "id": 125,
          "title": "Default",
          "price": "27.0",
          "compareAtPrice": "54.0"
        }
      ],
      "image": "/alkalive-assets/prod-sparkablack-individual.png",
      "images": [
        "/alkalive-assets/prod-sparkablack-individual.png"
      ],
      "bodyHtml": "<p>Discover elegance with Sparkablack.</p>",
      "descriptionAr": "اكتشف الأناقة مع سباركابلاك، أول ماء فوّار أسود في قطر سعة 330 مل.",
      "tags": [
        "premium",
        "sparkling",
        "black-water",
        "330ml"
      ]
    },
    {
      "id": 26,
      "title": "Luban Sparkling Water 250ml x 6",
      "titleAr": "مياه لبان الغازية 250 مل × 6",
      "handle": "luban-sparkling-250ml",
      "vendor": "Alkalive",
      "productType": "luban",
      "isNew": false,
      "isOffer": true,
      "variants": [
        {
          "id": 126,
          "title": "Default",
          "price": "14.0",
          "compareAtPrice": "28.0"
        }
      ],
      "image": "/alkalive-assets/prod-luban-spark-individual.png",
      "images": [
        "/alkalive-assets/prod-luban-spark-individual.png"
      ],
      "bodyHtml": "<p>Enjoy the sparkling vitality of Luban Sparkling Water.</p>",
      "descriptionAr": "استمتع بالحيوية الفوّارة مع مياه لبان الغازية سعة 250 مل.",
      "tags": [
        "luban",
        "sparkling",
        "frankincense",
        "250ml"
      ]
    },
    {
      "id": 27,
      "title": "Luban Sparkling Water 330ml x 6",
      "titleAr": "مياه لبان الغازية 330 مل × 6",
      "handle": "luban-sparkling-330ml",
      "vendor": "Alkalive",
      "productType": "luban",
      "isNew": false,
      "isOffer": true,
      "variants": [
        {
          "id": 127,
          "title": "Default",
          "price": "17.0",
          "compareAtPrice": "34.0"
        }
      ],
      "image": "/alkalive-assets/prod-luban-spark-individual.png",
      "images": [
        "/alkalive-assets/prod-luban-spark-individual.png"
      ],
      "bodyHtml": "<p>Enjoy the sparkling vitality of Luban Sparkling Water.</p>",
      "descriptionAr": "استمتع بالحيوية الفوّارة مع مياه لبان الغازية سعة 330 مل.",
      "tags": [
        "luban",
        "sparkling",
        "frankincense",
        "330ml"
      ]
    },
    {
      "id": 28,
      "title": "Luban Water 250ml x 6",
      "titleAr": "مياه لبان 250 مل × 6",
      "handle": "luban-water-250ml",
      "vendor": "Alkalive",
      "productType": "luban",
      "isNew": false,
      "isOffer": true,
      "variants": [
        {
          "id": 128,
          "title": "Default",
          "price": "12.5",
          "compareAtPrice": "25.0"
        }
      ],
      "image": "/alkalive-assets/prod-luban-water-individual.png",
      "images": [
        "/alkalive-assets/prod-luban-water-individual.png"
      ],
      "bodyHtml": "<p>Experience the pure essence of nature with Luban Water.</p>",
      "descriptionAr": "اختبر الجوهر النقي للطبيعة مع مياه لبان سعة 250 مل.",
      "tags": [
        "luban",
        "water",
        "frankincense",
        "250ml"
      ]
    },
    {
      "id": 29,
      "title": "Luban Water 330ml x 6",
      "titleAr": "مياه لبان 330 مل × 6",
      "handle": "luban-water-330ml",
      "vendor": "Alkalive",
      "productType": "luban",
      "isNew": false,
      "isOffer": true,
      "variants": [
        {
          "id": 129,
          "title": "Default",
          "price": "15.5",
          "compareAtPrice": "31.0"
        }
      ],
      "image": "/alkalive-assets/prod-luban-water-individual.png",
      "images": [
        "/alkalive-assets/prod-luban-water-individual.png"
      ],
      "bodyHtml": "<p>Experience the pure essence of nature with Luban Water.</p>",
      "descriptionAr": "اختبر الجوهر النقي للطبيعة مع مياه لبان سعة 330 مل.",
      "tags": [
        "luban",
        "water",
        "frankincense",
        "330ml"
      ]
    },
    {
      "id": 30,
      "title": "Luban Water 750ml x 6",
      "titleAr": "مياه لبان 750 مل × 6",
      "handle": "luban-water-750ml",
      "vendor": "Alkalive",
      "productType": "luban",
      "isNew": false,
      "isOffer": true,
      "variants": [
        {
          "id": 130,
          "title": "Default",
          "price": "27.5",
          "compareAtPrice": "55.0"
        }
      ],
      "image": "/alkalive-assets/prod-luban-water-individual.png",
      "images": [
        "/alkalive-assets/prod-luban-water-individual.png"
      ],
      "bodyHtml": "<p>Experience the pure essence of nature with Luban Water.</p>",
      "descriptionAr": "اختبر الجوهر النقي للطبيعة مع مياه لبان سعة 750 مل.",
      "tags": [
        "luban",
        "water",
        "frankincense",
        "750ml"
      ]
    },
    {
      "id": 31,
      "title": "Rare Mastiha Sparkling Water 330ml x 12",
      "titleAr": "مياه غازية نادرة بالمستكة 330 مل × 12",
      "handle": "mastiha-sparkling-330ml",
      "vendor": "Alkalive",
      "productType": "sparkling",
      "isNew": true,
      "isOffer": true,
      "variants": [
        {
          "id": 131,
          "title": "Default",
          "price": "75.0",
          "compareAtPrice": "150.0"
        }
      ],
      "image": "/alkalive-assets/prod-mastiha-individual.png",
      "images": [
        "/alkalive-assets/prod-mastiha-individual.png"
      ],
      "bodyHtml": "<p>Enjoy a unique refreshing experience with Sparkalive Mastiha.</p>",
      "descriptionAr": "استمتع بتجربة انتعاش فريدة من نوعها مع سباركالايف بالمستكة سعة 330 مل.",
      "tags": [
        "sparkling",
        "mastiha",
        "premium",
        "330ml"
      ]
    }
  ],
  "collections": {
    "all": [
      1,
      2,
      3,
      4,
      5,
      6,
      7,
      8,
      9,
      10,
      11,
      12,
      13,
      14,
      15,
      16,
      17,
      18,
      19,
      20,
      21,
      22,
      23,
      24,
      25,
      26,
      27,
      28,
      29,
      30,
      31
    ],
    "priced": [
      1,
      2,
      3,
      4,
      5,
      6,
      7,
      8
    ],
    "water": [
      1,
      2,
      3,
      4,
      5,
      9,
      10,
      13,
      14
    ],
    "glass": [
      16,
      17,
      18
    ],
    "sparkling": [
      19,
      20,
      21,
      22,
      23,
      31
    ],
    "premium": [
      24,
      25
    ],
    "luban": [
      26,
      27,
      28,
      29,
      30
    ],
    "kids": [
      11,
      12,
      13
    ],
    "sport": [
      15
    ],
    "bulk": [
      6,
      7,
      8
    ]
  }
}